{
  "Reporting": "100.0% (25,554 of 25,554) precincts reporting",
  "ReportingTime": "November 21, 2022, 4:20 p.m.",
  "raceTitle": "Supreme Court Justice - Statewide Results",
  "scraped_datetime": "2022-11-21T16:50:45.903351-08:00",
  "slug": "supreme-court",
  "supreme-court": [
    {
      "Name": "Patricia Guerrero",
      "noPercent": "28.7",
      "noVotes": "2379371",
      "yesPercent": "71.3",
      "yesVotes": "5900911"
    },
    {
      "Name": "Martin J. Jenkins",
      "noPercent": "30.3",
      "noVotes": "2414155",
      "yesPercent": "69.7",
      "yesVotes": "5556365"
    },
    {
      "Name": "Goodwin Liu",
      "noPercent": "30.4",
      "noVotes": "2461142",
      "yesPercent": "69.6",
      "yesVotes": "5632356"
    },
    {
      "Name": "Joshua P. Groban",
      "noPercent": "31.6",
      "noVotes": "2493759",
      "yesPercent": "68.4",
      "yesVotes": "5405373"
    }
  ],
  "url": "https://api.sos.ca.gov/returns/supreme-court"
}