{
  "Reporting": "100% (25,554 of 25,554) precincts reporting",
  "ReportingTime": "November 12, 2022, 3:56 p.m.",
  "candidates": [
    {
      "Name": "Shirley N. Weber",
      "Party": "Dem",
      "Percent": "58.8",
      "Votes": "3,981,509",
      "incumbent": false
    },
    {
      "Name": "Rob Bernosky",
      "Party": "Rep",
      "Percent": "41.2",
      "Votes": "2,784,357",
      "incumbent": false
    }
  ],
  "raceTitle": "Secretary of State - Statewide Results",
  "scraped_datetime": "2022-11-12T18:28:32.301569-08:00",
  "slug": "secretary-of-state",
  "url": "https://api.sos.ca.gov/returns/secretary-of-state"
}